pipeline/.monitor.py.swp
pipeline/__init__.py
pipeline/__main__.py
pipeline/backends/__init__.py
pipeline/backends/elasticsearch.py
pipeline/backends/http.py
pipeline/backends/httpserver.py
pipeline/backends/kafka.py
pipeline/backends/mongodb.py
pipeline/backends/pulsar.py
pipeline/backends/rabbitmq.py
pipeline/backends/redis.py
pipeline/backends/rq.py
pipeline/exception.py
pipeline/helpers.py
pipeline/importor.py
pipeline/manager.py
pipeline/message.py
pipeline/monitor.py
pipeline/tap.py
pipeline/version.py
pipeline/worker.py
tanbih_pipeline-0.12.18.dist-info/METADATA
tanbih_pipeline-0.12.18.dist-info/WHEEL
tanbih_pipeline-0.12.18.dist-info/entry_points.txt
tanbih_pipeline-0.12.18.dist-info/licenses/LICENSE
tanbih_pipeline-0.12.18.dist-info/RECORD
