Metadata-Version: 2.1
Name: tanbih-pipeline
Version: 0.12.18
Summary: data streaming on top of popular message queues
Home-page: https://github.com/yifan/pipeline
Author: Yifan Zhang
License: MIT
Project-URL: Homepage, https://github.com/yifan/pipeline
Project-URL: Repository, https://github.com/yifan/pipeline
Project-URL: Documentation, https://tanbih-pipeline.readthedocs.io/en/latest/
Requires-Python: <4.0,>=3.8
Requires-Dist: prometheus-client<1.0.0,>=0.21.0
Requires-Dist: zstandard<1.0.0,>=0.23.0
Requires-Dist: pydantic<3.0.0,>=2.9.2
Requires-Dist: redis<6.0.0,>=5.1.0
Requires-Dist: python-dotenv<2.0.0,>=1.0.1
Requires-Dist: pydantic-settings<3.0.0,>=2.2.1
Provides-Extra: full
Requires-Dist: confluent-kafka<3.0.0,>=2.5.3; extra == "full"
Requires-Dist: pulsar-client<4.0.0,>=1.3.0; extra == "full"
Requires-Dist: elasticsearch<9.0.0,>=7.15.2; extra == "full"
Requires-Dist: pymongo<5.0.0,>=3.12.3; extra == "full"
Requires-Dist: pika<2.0.0,>=1.3.2; extra == "full"
Requires-Dist: rq<2.0.0,>=1.16.2; extra == "full"
Provides-Extra: rabbitmq
Requires-Dist: pika<2.0.0,>=1.3.2; extra == "rabbitmq"
Provides-Extra: rq
Requires-Dist: rq<2.0.0,>=1.16.2; extra == "rq"
Provides-Extra: redis
Requires-Dist: redis<6.0.0,>=5.1.0; extra == "redis"
Provides-Extra: kafka
Requires-Dist: confluent-kafka<3.0.0,>=2.5.3; extra == "kafka"
Provides-Extra: pulsar
Requires-Dist: pulsar-client<4.0.0,>=1.3.0; extra == "pulsar"
Provides-Extra: elastic
Requires-Dist: elasticsearch<9.0.0,>=7.15.2; extra == "elastic"
Provides-Extra: mongodb
Requires-Dist: pymongo<5.0.0,>=3.12.3; extra == "mongodb"
Provides-Extra: http
Requires-Dist: aiohttp<4.0.0,>=3.10.7; extra == "http"
Provides-Extra: cli
Requires-Dist: click<9.0.0,>=8.1.7; extra == "cli"
Requires-Dist: python-dotenv<2.0.0,>=1.0.1; extra == "cli"
